LICENSE
MANIFEST.in
README.md
mdfigure.py
setup.py
markdown_figure.egg-info/PKG-INFO
markdown_figure.egg-info/SOURCES.txt
markdown_figure.egg-info/dependency_links.txt
markdown_figure.egg-info/requires.txt
markdown_figure.egg-info/top_level.txt