Metadata-Version: 1.1
Name: markdown-figure
Version: 0.0.1
Summary: Markdown extension which turns images into figures
Home-page: https://github.com/janwh/markdown-figures
Author: Jan Willhaus
Author-email: mail@janwillhaus.de
License: MIT
Keywords: markdown extension html figure
Platform: UNKNOWN
Classifier: Development Status :: 5 - Production/Stable
Classifier: Topic :: Text Processing :: Markup :: HTML
Classifier: License :: OSI Approved :: MIT License
Classifier: Programming Language :: Python :: 3
